factory_service/__init__.py
kawaii_lora/LoRa.py
kawaii_lora/__init__.py
kawaii_lora/board_conf.py
kawaii_lora/constants.py
kawaii_lora/my_types.py
Kawaii_LoRa-0.0.20.dist-info/METADATA
Kawaii_LoRa-0.0.20.dist-info/WHEEL
Kawaii_LoRa-0.0.20.dist-info/entry_points.txt
Kawaii_LoRa-0.0.20.dist-info/top_level.txt
Kawaii_LoRa-0.0.20.dist-info/RECORD
