Metadata-Version: 2.1
Name: Kawaii-LoRa
Version: 0.0.20
Summary: LoRa communication library for Raspberry Pi
Home-page: https://github.com/LuisTheProgrammer/Kawaii-LoRa
Author: Luis Di Matteo
Author-email: luiss.dimatteo@gmail.com
Classifier: Development Status :: 4 - Beta
Classifier: Intended Audience :: Developers
Classifier: Topic :: Software Development :: Libraries
Classifier: Topic :: System :: Hardware
Classifier: Operating System :: POSIX :: Linux
Classifier: Programming Language :: Python :: 3
Classifier: Programming Language :: Python :: 3.5
